{
    "config": {
        "postsPerPage": 5,
        "tagsPostsPerPage": "10",
        "authorsPostsPerPage": 5,
        "excerptLength": "145",
        "logo": "media/website/website.png"
    },
    "customConfig": {
        "pageMargin": "6vw",
        "pageWidth": "66rem",
        "entryWidth": "42rem",
        "borderRadius": "3",
        "baseline": "0.28333rem",
        "alignHero": "left",
        "textHero": "<h1><span style=\"color: #e67e23;\">شیرازلینوکس</span></h1>\n<p>ما یک جامعه متعهد به ترویج و توسعه نرم‌افزارهای آزاد و متن‌باز هستیم.</p>\n<p>در <strong><span style=\"color: #e67e23;\">شیرازلینوکس</span></strong>، بر این باوریم که دسترسی به فناوری باید <strong><span style=\"color: #2dc26b;\">برای همه آزاد باشد</span></strong>، ما به ترویج فرهنگ اشتراک‌گذاری دانش و همکاری در پروژه‌های مختلف اعتقاد داریم و تلاش می‌کنیم تا کاربران را در مسیر یادگیری و استفاده از سیستم‌عامل‌های مبتنی بر گنولینوکس یاری کنیم.</p>\n<p>یکی از اهداف مهم ما،<span style=\"color: #2dc26b;\"> <strong>برگزاری رویدادها، دورهمی‌ها، همایش‌ها، کنفرانس‌ها و بوت‌کمپ‌ها</strong> </span>است.</p>\n<p>این رویدادها فرصتی مناسب برای تبادل دانش، تجربیات و شبکه‌سازی میان علاقه‌مندان به نرم‌افزارهای آزاد فراهم می‌آورد و به ما کمک می‌کند تا <strong><span style=\"color: #e67e23;\">جامعه‌ای پویا و فعال</span></strong> بسازیم.</p>\n<hr>",
        "heightHero": "70vh",
        "uploadHero": "media/website/img2.jpeg",
        "uploadHeroAlt": "Image",
        "uploadHeroCaption": "شیرازلینوکس",
        "relatedPostsNumber": "3",
        "alignFeed": "center",
        "feedFeaturedImage": true,
        "feedFeaturedImageSize": "15",
        "feedAvatar": false,
        "feedAuthor": false,
        "feedDate": false,
        "feedDateType": "published",
        "feedtReadMore": true,
        "navbarHeight": "4rem",
        "submenu": "auto",
        "submenuWidth": "240",
        "mobilemenu": "sidebar",
        "mobilemenuExpandableSubmenus": true,
        "colorScheme": "light",
        "primaryColor": "#D73A42",
        "primaryDarkColor": "#FFC074",
        "fontBody": "vazirmatn",
        "disableFontBodyItalic": false,
        "fontHeadings": "vazirmatn",
        "disableFontHeadingsItalic": false,
        "fontMenu": "var(--body-font)",
        "fontLogo": "var(--body-font)",
        "minFontSize": "1.1",
        "maxFontSize": "1.2",
        "lineHeight": "1.7",
        "letterSpacing": "0",
        "fontBodyWeight": "400",
        "fontBoldWeight": "600",
        "fontHeadignsWeight": "500",
        "fontHeadingsStyle": "normal",
        "fontHeadingsLineHeight": "1.2",
        "fontHeadingsletterSpacing": "0",
        "fontHeadingsTransform": "none",
        "shareFacebook": true,
        "shareTwitter": true,
        "shareTwitterName": "@shirazlinux",
        "sharePinterest": false,
        "shareMix": false,
        "shareLinkedin": true,
        "shareBuffer": false,
        "shareWhatsApp": true,
        "socialButtons": true,
        "socialFacebook": "https://t.me/shirazlinuxcommunity",
        "socialTwitter": "https://x.com/shirazlinux?t=JClI2d2TTZheGqQQtF0xqQ&s=09",
        "socialInstagram": "https://www.instagram.com/shirazlinux?igsh=Y3RzZ3VuZnB0aW02",
        "socialLinkedin": "https://www.linkedin.com/posts/shirazlinux",
        "socialVimeo": "https://github.com/shirazlinux/sudoshz.ir",
        "socialPinterest": "",
        "socialYoutube": "https://youtube.com/@shirazlinux?si=BTI0Hh6DIRqfp9XW",
        "copyrightText": "<p>این وب‌سایت تحت لایسنس MIT منتشر شده است<br>حق نشر <strong class=\"copyleft\">©</strong> 2023 <a href=\"sudoshz.ir\" target=\"_blank\" rel=\"noopener\">شیرازلینوکس</a><br>قدرت گرفته شده از <a href=\"https://getpublii.com\">Publii</a></p>",
        "searchFeature": false,
        "createSearchPage": false,
        "galleryItemGap": "calc(var(--baseline) * 1.5)",
        "backToTopButton": true,
        "formatDate": "custom",
        "formatDateCustom": "Y/MM/DD",
        "lazyLoadEffect": "fadein",
        "faviconUpload": "media/website/webicon320.png",
        "faviconExtension": "image/png",
        "fontBodyItalic": false,
        "fontHeadingsItalic": false
    },
    "postConfig": {
        "displayDate": 1,
        "displayAuthor": 1,
        "displayLastUpdatedDate": 1,
        "displayTags": 1,
        "displayShareButtons": 1,
        "displayAuthorBio": 1,
        "displayPostNavigation": 1,
        "displayRelatedPosts": 1,
        "displayComments": "1"
    },
    "tagConfig": {
        "displayFeaturedImage": 1,
        "displayPostCounter": 1,
        "displayDescription": 1,
        "displayPostList": 1
    },
    "authorConfig": {
        "displayFeaturedImage": 1,
        "displayAvatar": 1,
        "displayPostCounter": 1,
        "displayDescription": 1,
        "displayWebsite": 1,
        "displayPostList": 1
    },
    "defaultTemplates": {
        "post": ""
    }
}